x2doc/__init__.py
x2doc/cli.py
x2doc-0.0.0.dist-info/METADATA
x2doc-0.0.0.dist-info/WHEEL
x2doc-0.0.0.dist-info/entry_points.txt
x2doc-0.0.0.dist-info/RECORD
