Metadata-Version: 2.4
Name: x2doc
Version: 0.0.0
Summary: Transform X into documentation, where X = {chats, commits, ⋯}
Project-URL: home, https://github.com/kaycebasques/x2doc
Project-URL: issues, https://github.com/kaycebasques/x2doc/issues
Author-email: Kayce Basques <kaycebasques@gmail.com>
License-Expression: Apache-2.0
Requires-Python: >=3.14
